[
    {
        "codgeo": 56001,
        "libgeo": "Allaire",
        "an": 2021,
        "part_proprio": 74.3
    },
    {
        "codgeo": 56002,
        "libgeo": "Ambon",
        "an": 2021,
        "part_proprio": 72.3
    },
    {
        "codgeo": 56003,
        "libgeo": "Arradon",
        "an": 2021,
        "part_proprio": 71.8
    },
    {
        "codgeo": 56004,
        "libgeo": "Arzal",
        "an": 2021,
        "part_proprio": 68.1
    },
    {
        "codgeo": 56005,
        "libgeo": "Arzon",
        "an": 2021,
        "part_proprio": 72.1
    },
    {
        "codgeo": 56006,
        "libgeo": "Augan",
        "an": 2021,
        "part_proprio": 73.1
    },
    {
        "codgeo": 56007,
        "libgeo": "Auray",
        "an": 2021,
        "part_proprio": 46.8
    },
    {
        "codgeo": 56008,
        "libgeo": "Baden",
        "an": 2021,
        "part_proprio": 75.8
    },
    {
        "codgeo": 56009,
        "libgeo": "Bangor",
        "an": 2021,
        "part_proprio": 76.2
    },
    {
        "codgeo": 56010,
        "libgeo": "Baud",
        "an": 2021,
        "part_proprio": 74.2
    },
    {
        "codgeo": 56011,
        "libgeo": "Béganne",
        "an": 2021,
        "part_proprio": 83.8
    },
    {
        "codgeo": 56012,
        "libgeo": "Beignon",
        "an": 2021,
        "part_proprio": 72.8
    },
    {
        "codgeo": 56013,
        "libgeo": "Belz",
        "an": 2021,
        "part_proprio": 76.6
    },
    {
        "codgeo": 56014,
        "libgeo": "Berné",
        "an": 2021,
        "part_proprio": 83.0
    },
    {
        "codgeo": 56015,
        "libgeo": "Berric",
        "an": 2021,
        "part_proprio": 78.2
    },
    {
        "codgeo": 56017,
        "libgeo": "Bignan",
        "an": 2021,
        "part_proprio": 77.1
    },
    {
        "codgeo": 56018,
        "libgeo": "Billiers",
        "an": 2021,
        "part_proprio": 79.1
    },
    {
        "codgeo": 56019,
        "libgeo": "Billio",
        "an": 2021,
        "part_proprio": 83.2
    },
    {
        "codgeo": 56020,
        "libgeo": "Bohal",
        "an": 2021,
        "part_proprio": 81.6
    },
    {
        "codgeo": 56021,
        "libgeo": "Brandérion",
        "an": 2021,
        "part_proprio": 76.5
    },
    {
        "codgeo": 56022,
        "libgeo": "Brandivy",
        "an": 2021,
        "part_proprio": 83.3
    },
    {
        "codgeo": 56023,
        "libgeo": "Brech",
        "an": 2021,
        "part_proprio": 77.7
    },
    {
        "codgeo": 56024,
        "libgeo": "Bréhan",
        "an": 2021,
        "part_proprio": 80.2
    },
    {
        "codgeo": 56025,
        "libgeo": "Brignac",
        "an": 2021,
        "part_proprio": 86.5
    },
    {
        "codgeo": 56026,
        "libgeo": "Bubry",
        "an": 2021,
        "part_proprio": 83.0
    },
    {
        "codgeo": 56027,
        "libgeo": "Buléon",
        "an": 2021,
        "part_proprio": 78.1
    },
    {
        "codgeo": 56028,
        "libgeo": "Caden",
        "an": 2021,
        "part_proprio": 81.6
    },
    {
        "codgeo": 56029,
        "libgeo": "Calan",
        "an": 2021,
        "part_proprio": 80.2
    },
    {
        "codgeo": 56030,
        "libgeo": "Camoël",
        "an": 2021,
        "part_proprio": 75.4
    },
    {
        "codgeo": 56031,
        "libgeo": "Camors",
        "an": 2021,
        "part_proprio": 83.3
    },
    {
        "codgeo": 56032,
        "libgeo": "Campénéac",
        "an": 2021,
        "part_proprio": 74.1
    },
    {
        "codgeo": 56033,
        "libgeo": "Carentoir",
        "an": 2021,
        "part_proprio": 75.4
    },
    {
        "codgeo": 56034,
        "libgeo": "Carnac",
        "an": 2021,
        "part_proprio": 72.9
    },
    {
        "codgeo": 56035,
        "libgeo": "Caro",
        "an": 2021,
        "part_proprio": 77.9
    },
    {
        "codgeo": 56036,
        "libgeo": "Caudan",
        "an": 2021,
        "part_proprio": 76.4
    },
    {
        "codgeo": 56039,
        "libgeo": "La Chapelle-Neuve",
        "an": 2021,
        "part_proprio": 84.1
    },
    {
        "codgeo": 56040,
        "libgeo": "Cléguer",
        "an": 2021,
        "part_proprio": 84.4
    },
    {
        "codgeo": 56041,
        "libgeo": "Cléguérec",
        "an": 2021,
        "part_proprio": 83.0
    },
    {
        "codgeo": 56042,
        "libgeo": "Colpo",
        "an": 2021,
        "part_proprio": 79.2
    },
    {
        "codgeo": 56043,
        "libgeo": "Concoret",
        "an": 2021,
        "part_proprio": 75.5
    },
    {
        "codgeo": 56044,
        "libgeo": "Cournon",
        "an": 2021,
        "part_proprio": 83.5
    },
    {
        "codgeo": 56045,
        "libgeo": "Le Cours",
        "an": 2021,
        "part_proprio": 76.2
    },
    {
        "codgeo": 56046,
        "libgeo": "Crach",
        "an": 2021,
        "part_proprio": 79.6
    },
    {
        "codgeo": 56047,
        "libgeo": "Crédin",
        "an": 2021,
        "part_proprio": 86.5
    },
    {
        "codgeo": 56048,
        "libgeo": "Le Croisty",
        "an": 2021,
        "part_proprio": 83.2
    },
    {
        "codgeo": 56050,
        "libgeo": "La Croix-Helléan",
        "an": 2021,
        "part_proprio": 86.6
    },
    {
        "codgeo": 56051,
        "libgeo": "Cruguel",
        "an": 2021,
        "part_proprio": 78.4
    },
    {
        "codgeo": 56052,
        "libgeo": "Damgan",
        "an": 2021,
        "part_proprio": 77.4
    },
    {
        "codgeo": 56053,
        "libgeo": "Elven",
        "an": 2021,
        "part_proprio": 65.6
    },
    {
        "codgeo": 56054,
        "libgeo": "Erdeven",
        "an": 2021,
        "part_proprio": 75.5
    },
    {
        "codgeo": 56055,
        "libgeo": "Étel",
        "an": 2021,
        "part_proprio": 71.2
    },
    {
        "codgeo": 56056,
        "libgeo": "Évriguet",
        "an": 2021,
        "part_proprio": 81.6
    },
    {
        "codgeo": 56057,
        "libgeo": "Le Faouët",
        "an": 2021,
        "part_proprio": 74.8
    },
    {
        "codgeo": 56058,
        "libgeo": "Férel",
        "an": 2021,
        "part_proprio": 80.9
    },
    {
        "codgeo": 56060,
        "libgeo": "Les Fougerêts",
        "an": 2021,
        "part_proprio": 79.6
    },
    {
        "codgeo": 56061,
        "libgeo": "La Gacilly",
        "an": 2021,
        "part_proprio": 74.2
    },
    {
        "codgeo": 56062,
        "libgeo": "Gâvres",
        "an": 2021,
        "part_proprio": 59.9
    },
    {
        "codgeo": 56063,
        "libgeo": "Gestel",
        "an": 2021,
        "part_proprio": 78.3
    },
    {
        "codgeo": 56065,
        "libgeo": "Gourhel",
        "an": 2021,
        "part_proprio": 80.5
    },
    {
        "codgeo": 56066,
        "libgeo": "Gourin",
        "an": 2021,
        "part_proprio": 78.2
    },
    {
        "codgeo": 56067,
        "libgeo": "Grand-Champ",
        "an": 2021,
        "part_proprio": 78.5
    },
    {
        "codgeo": 56068,
        "libgeo": "La Grée-Saint-Laurent",
        "an": 2021,
        "part_proprio": 87.0
    },
    {
        "codgeo": 56069,
        "libgeo": "Groix",
        "an": 2021,
        "part_proprio": 76.1
    },
    {
        "codgeo": 56070,
        "libgeo": "Guégon",
        "an": 2021,
        "part_proprio": 82.5
    },
    {
        "codgeo": 56071,
        "libgeo": "Guéhenno",
        "an": 2021,
        "part_proprio": 80.7
    },
    {
        "codgeo": 56072,
        "libgeo": "Gueltas",
        "an": 2021,
        "part_proprio": 79.2
    },
    {
        "codgeo": 56073,
        "libgeo": "Guémené-sur-Scorff",
        "an": 2021,
        "part_proprio": 63.8
    },
    {
        "codgeo": 56074,
        "libgeo": "Guénin",
        "an": 2021,
        "part_proprio": 81.4
    },
    {
        "codgeo": 56075,
        "libgeo": "Guer",
        "an": 2021,
        "part_proprio": 61.5
    },
    {
        "codgeo": 56076,
        "libgeo": "Guern",
        "an": 2021,
        "part_proprio": 82.8
    },
    {
        "codgeo": 56077,
        "libgeo": "Le Guerno",
        "an": 2021,
        "part_proprio": 75.4
    },
    {
        "codgeo": 56078,
        "libgeo": "Guidel",
        "an": 2021,
        "part_proprio": 70.5
    },
    {
        "codgeo": 56079,
        "libgeo": "Guillac",
        "an": 2021,
        "part_proprio": 82.1
    },
    {
        "codgeo": 56080,
        "libgeo": "Guilliers",
        "an": 2021,
        "part_proprio": 83.6
    },
    {
        "codgeo": 56081,
        "libgeo": "Guiscriff",
        "an": 2021,
        "part_proprio": 84.0
    },
    {
        "codgeo": 56082,
        "libgeo": "Helléan",
        "an": 2021,
        "part_proprio": 80.3
    },
    {
        "codgeo": 56083,
        "libgeo": "Hennebont",
        "an": 2021,
        "part_proprio": 58.9
    },
    {
        "codgeo": 56084,
        "libgeo": "Le Hézo",
        "an": 2021,
        "part_proprio": 75.1
    },
    {
        "codgeo": 56085,
        "libgeo": "Hœdic",
        "an": 2021,
        "part_proprio": 64.2
    },
    {
        "codgeo": 56086,
        "libgeo": "Île-d'Houat",
        "an": 2021,
        "part_proprio": 76.7
    },
    {
        "codgeo": 56087,
        "libgeo": "Île-aux-Moines",
        "an": 2021,
        "part_proprio": 73.0
    },
    {
        "codgeo": 56088,
        "libgeo": "Île-d'Arz",
        "an": 2021,
        "part_proprio": 75.6
    },
    {
        "codgeo": 56089,
        "libgeo": "Inguiniel",
        "an": 2021,
        "part_proprio": 84.2
    },
    {
        "codgeo": 56090,
        "libgeo": "Inzinzac-Lochrist",
        "an": 2021,
        "part_proprio": 79.0
    },
    {
        "codgeo": 56091,
        "libgeo": "Josselin",
        "an": 2021,
        "part_proprio": 60.8
    },
    {
        "codgeo": 56092,
        "libgeo": "Kerfourn",
        "an": 2021,
        "part_proprio": 84.3
    },
    {
        "codgeo": 56093,
        "libgeo": "Kergrist",
        "an": 2021,
        "part_proprio": 81.9
    },
    {
        "codgeo": 56094,
        "libgeo": "Kervignac",
        "an": 2021,
        "part_proprio": 81.1
    },
    {
        "codgeo": 56096,
        "libgeo": "Landaul",
        "an": 2021,
        "part_proprio": 81.4
    },
    {
        "codgeo": 56097,
        "libgeo": "Landévant",
        "an": 2021,
        "part_proprio": 77.3
    },
    {
        "codgeo": 56098,
        "libgeo": "Lanester",
        "an": 2021,
        "part_proprio": 57.5
    },
    {
        "codgeo": 56099,
        "libgeo": "Langoëlan",
        "an": 2021,
        "part_proprio": 78.7
    },
    {
        "codgeo": 56100,
        "libgeo": "Langonnet",
        "an": 2021,
        "part_proprio": 82.4
    },
    {
        "codgeo": 56101,
        "libgeo": "Languidic",
        "an": 2021,
        "part_proprio": 77.3
    },
    {
        "codgeo": 56102,
        "libgeo": "Forges de Lanouée",
        "an": 2021,
        "part_proprio": 81.8
    },
    {
        "codgeo": 56103,
        "libgeo": "Lantillac",
        "an": 2021,
        "part_proprio": 83.1
    },
    {
        "codgeo": 56104,
        "libgeo": "Lanvaudan",
        "an": 2021,
        "part_proprio": 86.4
    },
    {
        "codgeo": 56105,
        "libgeo": "Lanvénégen",
        "an": 2021,
        "part_proprio": 81.9
    },
    {
        "codgeo": 56106,
        "libgeo": "Larmor-Baden",
        "an": 2021,
        "part_proprio": 76.1
    },
    {
        "codgeo": 56107,
        "libgeo": "Larmor-Plage",
        "an": 2021,
        "part_proprio": 70.4
    },
    {
        "codgeo": 56108,
        "libgeo": "Larré",
        "an": 2021,
        "part_proprio": 83.5
    },
    {
        "codgeo": 56109,
        "libgeo": "Lauzach",
        "an": 2021,
        "part_proprio": 80.4
    },
    {
        "codgeo": 56110,
        "libgeo": "Lignol",
        "an": 2021,
        "part_proprio": 84.0
    },
    {
        "codgeo": 56111,
        "libgeo": "Limerzel",
        "an": 2021,
        "part_proprio": 80.7
    },
    {
        "codgeo": 56112,
        "libgeo": "Lizio",
        "an": 2021,
        "part_proprio": 78.2
    },
    {
        "codgeo": 56113,
        "libgeo": "Locmalo",
        "an": 2021,
        "part_proprio": 84.5
    },
    {
        "codgeo": 56114,
        "libgeo": "Locmaria",
        "an": 2021,
        "part_proprio": 74.6
    },
    {
        "codgeo": 56115,
        "libgeo": "Locmaria-Grand-Champ",
        "an": 2021,
        "part_proprio": 82.2
    },
    {
        "codgeo": 56116,
        "libgeo": "Locmariaquer",
        "an": 2021,
        "part_proprio": 78.1
    },
    {
        "codgeo": 56117,
        "libgeo": "Locminé",
        "an": 2021,
        "part_proprio": 53.6
    },
    {
        "codgeo": 56118,
        "libgeo": "Locmiquélic",
        "an": 2021,
        "part_proprio": 75.8
    },
    {
        "codgeo": 56119,
        "libgeo": "Locoal-Mendon",
        "an": 2021,
        "part_proprio": 78.3
    },
    {
        "codgeo": 56120,
        "libgeo": "Locqueltas",
        "an": 2021,
        "part_proprio": 80.2
    },
    {
        "codgeo": 56121,
        "libgeo": "Lorient",
        "an": 2021,
        "part_proprio": 42.7
    },
    {
        "codgeo": 56122,
        "libgeo": "Loyat",
        "an": 2021,
        "part_proprio": 79.5
    },
    {
        "codgeo": 56123,
        "libgeo": "Malansac",
        "an": 2021,
        "part_proprio": 79.4
    },
    {
        "codgeo": 56124,
        "libgeo": "Malestroit",
        "an": 2021,
        "part_proprio": 64.2
    },
    {
        "codgeo": 56125,
        "libgeo": "Malguénac",
        "an": 2021,
        "part_proprio": 86.8
    },
    {
        "codgeo": 56126,
        "libgeo": "Marzan",
        "an": 2021,
        "part_proprio": 80.0
    },
    {
        "codgeo": 56127,
        "libgeo": "Mauron",
        "an": 2021,
        "part_proprio": 78.4
    },
    {
        "codgeo": 56128,
        "libgeo": "Melrand",
        "an": 2021,
        "part_proprio": 79.4
    },
    {
        "codgeo": 56129,
        "libgeo": "Ménéac",
        "an": 2021,
        "part_proprio": 80.1
    },
    {
        "codgeo": 56130,
        "libgeo": "Merlevenez",
        "an": 2021,
        "part_proprio": 79.6
    },
    {
        "codgeo": 56131,
        "libgeo": "Meslan",
        "an": 2021,
        "part_proprio": 83.4
    },
    {
        "codgeo": 56132,
        "libgeo": "Meucon",
        "an": 2021,
        "part_proprio": 72.9
    },
    {
        "codgeo": 56133,
        "libgeo": "Missiriac",
        "an": 2021,
        "part_proprio": 86.9
    },
    {
        "codgeo": 56134,
        "libgeo": "Mohon",
        "an": 2021,
        "part_proprio": 87.1
    },
    {
        "codgeo": 56135,
        "libgeo": "Molac",
        "an": 2021,
        "part_proprio": 82.0
    },
    {
        "codgeo": 56136,
        "libgeo": "Monteneuf",
        "an": 2021,
        "part_proprio": 81.7
    },
    {
        "codgeo": 56137,
        "libgeo": "Monterblanc",
        "an": 2021,
        "part_proprio": 79.2
    },
    {
        "codgeo": 56139,
        "libgeo": "Montertelot",
        "an": 2021,
        "part_proprio": 90.7
    },
    {
        "codgeo": 56140,
        "libgeo": "Moréac",
        "an": 2021,
        "part_proprio": 80.0
    },
    {
        "codgeo": 56141,
        "libgeo": "Moustoir-Ac",
        "an": 2021,
        "part_proprio": 83.7
    },
    {
        "codgeo": 56143,
        "libgeo": "Muzillac",
        "an": 2021,
        "part_proprio": 69.5
    },
    {
        "codgeo": 56144,
        "libgeo": "Évellys",
        "an": 2021,
        "part_proprio": 82.7
    },
    {
        "codgeo": 56145,
        "libgeo": "Néant-sur-Yvel",
        "an": 2021,
        "part_proprio": 77.4
    },
    {
        "codgeo": 56146,
        "libgeo": "Neulliac",
        "an": 2021,
        "part_proprio": 81.6
    },
    {
        "codgeo": 56147,
        "libgeo": "Nivillac",
        "an": 2021,
        "part_proprio": 77.7
    },
    {
        "codgeo": 56148,
        "libgeo": "Nostang",
        "an": 2021,
        "part_proprio": 79.6
    },
    {
        "codgeo": 56149,
        "libgeo": "Noyal-Muzillac",
        "an": 2021,
        "part_proprio": 77.1
    },
    {
        "codgeo": 56151,
        "libgeo": "Noyal-Pontivy",
        "an": 2021,
        "part_proprio": 79.8
    },
    {
        "codgeo": 56152,
        "libgeo": "Le Palais",
        "an": 2021,
        "part_proprio": 64.4
    },
    {
        "codgeo": 56153,
        "libgeo": "Péaule",
        "an": 2021,
        "part_proprio": 74.9
    },
    {
        "codgeo": 56154,
        "libgeo": "Peillac",
        "an": 2021,
        "part_proprio": 79.1
    },
    {
        "codgeo": 56155,
        "libgeo": "Pénestin",
        "an": 2021,
        "part_proprio": 73.9
    },
    {
        "codgeo": 56156,
        "libgeo": "Persquen",
        "an": 2021,
        "part_proprio": 86.1
    },
    {
        "codgeo": 56157,
        "libgeo": "Plaudren",
        "an": 2021,
        "part_proprio": 85.8
    },
    {
        "codgeo": 56158,
        "libgeo": "Plescop",
        "an": 2021,
        "part_proprio": 57.1
    },
    {
        "codgeo": 56159,
        "libgeo": "Pleucadeuc",
        "an": 2021,
        "part_proprio": 77.2
    },
    {
        "codgeo": 56160,
        "libgeo": "Pleugriffet",
        "an": 2021,
        "part_proprio": 78.0
    },
    {
        "codgeo": 56161,
        "libgeo": "Ploemel",
        "an": 2021,
        "part_proprio": 82.9
    },
    {
        "codgeo": 56162,
        "libgeo": "Ploemeur",
        "an": 2021,
        "part_proprio": 75.3
    },
    {
        "codgeo": 56163,
        "libgeo": "Ploërdut",
        "an": 2021,
        "part_proprio": 84.2
    },
    {
        "codgeo": 56164,
        "libgeo": "Ploeren",
        "an": 2021,
        "part_proprio": 66.0
    },
    {
        "codgeo": 56165,
        "libgeo": "Ploërmel",
        "an": 2021,
        "part_proprio": 62.9
    },
    {
        "codgeo": 56166,
        "libgeo": "Plouay",
        "an": 2021,
        "part_proprio": 71.6
    },
    {
        "codgeo": 56167,
        "libgeo": "Plougoumelen",
        "an": 2021,
        "part_proprio": 82.5
    },
    {
        "codgeo": 56168,
        "libgeo": "Plouharnel",
        "an": 2021,
        "part_proprio": 78.5
    },
    {
        "codgeo": 56169,
        "libgeo": "Plouhinec",
        "an": 2021,
        "part_proprio": 79.8
    },
    {
        "codgeo": 56170,
        "libgeo": "Plouray",
        "an": 2021,
        "part_proprio": 77.0
    },
    {
        "codgeo": 56171,
        "libgeo": "Pluherlin",
        "an": 2021,
        "part_proprio": 78.6
    },
    {
        "codgeo": 56172,
        "libgeo": "Plumelec",
        "an": 2021,
        "part_proprio": 75.5
    },
    {
        "codgeo": 56173,
        "libgeo": "Pluméliau-Bieuzy",
        "an": 2021,
        "part_proprio": 82.5
    },
    {
        "codgeo": 56174,
        "libgeo": "Plumelin",
        "an": 2021,
        "part_proprio": 81.2
    },
    {
        "codgeo": 56175,
        "libgeo": "Plumergat",
        "an": 2021,
        "part_proprio": 79.4
    },
    {
        "codgeo": 56176,
        "libgeo": "Pluneret",
        "an": 2021,
        "part_proprio": 70.0
    },
    {
        "codgeo": 56177,
        "libgeo": "Pluvigner",
        "an": 2021,
        "part_proprio": 78.8
    },
    {
        "codgeo": 56178,
        "libgeo": "Pontivy",
        "an": 2021,
        "part_proprio": 51.1
    },
    {
        "codgeo": 56179,
        "libgeo": "Pont-Scorff",
        "an": 2021,
        "part_proprio": 76.5
    },
    {
        "codgeo": 56180,
        "libgeo": "Porcaro",
        "an": 2021,
        "part_proprio": 82.9
    },
    {
        "codgeo": 56181,
        "libgeo": "Port-Louis",
        "an": 2021,
        "part_proprio": 66.1
    },
    {
        "codgeo": 56182,
        "libgeo": "Priziac",
        "an": 2021,
        "part_proprio": 78.8
    },
    {
        "codgeo": 56184,
        "libgeo": "Questembert",
        "an": 2021,
        "part_proprio": 68.2
    },
    {
        "codgeo": 56185,
        "libgeo": "Quéven",
        "an": 2021,
        "part_proprio": 76.6
    },
    {
        "codgeo": 56186,
        "libgeo": "Quiberon",
        "an": 2021,
        "part_proprio": 67.4
    },
    {
        "codgeo": 56188,
        "libgeo": "Quistinic",
        "an": 2021,
        "part_proprio": 83.6
    },
    {
        "codgeo": 56189,
        "libgeo": "Radenac",
        "an": 2021,
        "part_proprio": 79.9
    },
    {
        "codgeo": 56190,
        "libgeo": "Réguiny",
        "an": 2021,
        "part_proprio": 76.9
    },
    {
        "codgeo": 56191,
        "libgeo": "Réminiac",
        "an": 2021,
        "part_proprio": 78.7
    },
    {
        "codgeo": 56193,
        "libgeo": "Riantec",
        "an": 2021,
        "part_proprio": 74.4
    },
    {
        "codgeo": 56194,
        "libgeo": "Rieux",
        "an": 2021,
        "part_proprio": 77.9
    },
    {
        "codgeo": 56195,
        "libgeo": "La Roche-Bernard",
        "an": 2021,
        "part_proprio": 47.4
    },
    {
        "codgeo": 56196,
        "libgeo": "Rochefort-en-Terre",
        "an": 2021,
        "part_proprio": 68.6
    },
    {
        "codgeo": 56197,
        "libgeo": "Val d'Oust",
        "an": 2021,
        "part_proprio": 78.0
    },
    {
        "codgeo": 56198,
        "libgeo": "Rohan",
        "an": 2021,
        "part_proprio": 78.5
    },
    {
        "codgeo": 56199,
        "libgeo": "Roudouallec",
        "an": 2021,
        "part_proprio": 86.5
    },
    {
        "codgeo": 56200,
        "libgeo": "Ruffiac",
        "an": 2021,
        "part_proprio": 79.3
    },
    {
        "codgeo": 56201,
        "libgeo": "Le Saint",
        "an": 2021,
        "part_proprio": 88.7
    },
    {
        "codgeo": 56202,
        "libgeo": "Saint-Abraham",
        "an": 2021,
        "part_proprio": 77.9
    },
    {
        "codgeo": 56203,
        "libgeo": "Saint-Aignan",
        "an": 2021,
        "part_proprio": 82.0
    },
    {
        "codgeo": 56204,
        "libgeo": "Saint-Allouestre",
        "an": 2021,
        "part_proprio": 78.7
    },
    {
        "codgeo": 56205,
        "libgeo": "Saint-Armel",
        "an": 2021,
        "part_proprio": 80.8
    },
    {
        "codgeo": 56206,
        "libgeo": "Saint-Avé",
        "an": 2021,
        "part_proprio": 61.6
    },
    {
        "codgeo": 56207,
        "libgeo": "Saint-Barthélemy",
        "an": 2021,
        "part_proprio": 83.2
    },
    {
        "codgeo": 56208,
        "libgeo": "Saint-Brieuc-de-Mauron",
        "an": 2021,
        "part_proprio": 79.3
    },
    {
        "codgeo": 56209,
        "libgeo": "Sainte-Brigitte",
        "an": 2021,
        "part_proprio": 83.9
    },
    {
        "codgeo": 56210,
        "libgeo": "Saint-Caradec-Trégomel",
        "an": 2021,
        "part_proprio": 84.9
    },
    {
        "codgeo": 56211,
        "libgeo": "Saint-Congard",
        "an": 2021,
        "part_proprio": 86.3
    },
    {
        "codgeo": 56212,
        "libgeo": "Saint-Dolay",
        "an": 2021,
        "part_proprio": 81.5
    },
    {
        "codgeo": 56213,
        "libgeo": "Saint-Gérand-Croixanvec",
        "an": 2021,
        "part_proprio": 77.9
    },
    {
        "codgeo": 56214,
        "libgeo": "Saint-Gildas-de-Rhuys",
        "an": 2021,
        "part_proprio": 82.8
    },
    {
        "codgeo": 56215,
        "libgeo": "Saint-Gonnery",
        "an": 2021,
        "part_proprio": 81.8
    },
    {
        "codgeo": 56216,
        "libgeo": "Saint-Gorgon",
        "an": 2021,
        "part_proprio": 76.2
    },
    {
        "codgeo": 56218,
        "libgeo": "Saint-Gravé",
        "an": 2021,
        "part_proprio": 82.4
    },
    {
        "codgeo": 56219,
        "libgeo": "Saint-Guyomard",
        "an": 2021,
        "part_proprio": 87.7
    },
    {
        "codgeo": 56220,
        "libgeo": "Sainte-Hélène",
        "an": 2021,
        "part_proprio": 84.0
    },
    {
        "codgeo": 56221,
        "libgeo": "Saint-Jacut-les-Pins",
        "an": 2021,
        "part_proprio": 77.4
    },
    {
        "codgeo": 56222,
        "libgeo": "Saint-Jean-Brévelay",
        "an": 2021,
        "part_proprio": 74.7
    },
    {
        "codgeo": 56223,
        "libgeo": "Saint-Jean-la-Poterie",
        "an": 2021,
        "part_proprio": 84.1
    },
    {
        "codgeo": 56224,
        "libgeo": "Saint-Laurent-sur-Oust",
        "an": 2021,
        "part_proprio": 78.8
    },
    {
        "codgeo": 56225,
        "libgeo": "Saint-Léry",
        "an": 2021,
        "part_proprio": 75.3
    },
    {
        "codgeo": 56226,
        "libgeo": "Saint-Malo-de-Beignon",
        "an": 2021,
        "part_proprio": 73.1
    },
    {
        "codgeo": 56227,
        "libgeo": "Saint-Malo-des-Trois-Fontaines",
        "an": 2021,
        "part_proprio": 81.1
    },
    {
        "codgeo": 56228,
        "libgeo": "Saint-Marcel",
        "an": 2021,
        "part_proprio": 69.4
    },
    {
        "codgeo": 56229,
        "libgeo": "Saint-Martin-sur-Oust",
        "an": 2021,
        "part_proprio": 82.0
    },
    {
        "codgeo": 56230,
        "libgeo": "Saint-Nicolas-du-Tertre",
        "an": 2021,
        "part_proprio": 78.2
    },
    {
        "codgeo": 56231,
        "libgeo": "Saint-Nolff",
        "an": 2021,
        "part_proprio": 79.3
    },
    {
        "codgeo": 56232,
        "libgeo": "Saint-Perreux",
        "an": 2021,
        "part_proprio": 84.1
    },
    {
        "codgeo": 56233,
        "libgeo": "Saint-Philibert",
        "an": 2021,
        "part_proprio": 77.8
    },
    {
        "codgeo": 56234,
        "libgeo": "Saint-Pierre-Quiberon",
        "an": 2021,
        "part_proprio": 77.4
    },
    {
        "codgeo": 56236,
        "libgeo": "Saint-Servant",
        "an": 2021,
        "part_proprio": 85.4
    },
    {
        "codgeo": 56237,
        "libgeo": "Saint-Thuriau",
        "an": 2021,
        "part_proprio": 80.7
    },
    {
        "codgeo": 56238,
        "libgeo": "Saint-Tugdual",
        "an": 2021,
        "part_proprio": 81.3
    },
    {
        "codgeo": 56239,
        "libgeo": "Saint-Vincent-sur-Oust",
        "an": 2021,
        "part_proprio": 81.1
    },
    {
        "codgeo": 56240,
        "libgeo": "Sarzeau",
        "an": 2021,
        "part_proprio": 72.6
    },
    {
        "codgeo": 56241,
        "libgeo": "Sauzon",
        "an": 2021,
        "part_proprio": 71.9
    },
    {
        "codgeo": 56242,
        "libgeo": "Séglien",
        "an": 2021,
        "part_proprio": 84.8
    },
    {
        "codgeo": 56243,
        "libgeo": "Séné",
        "an": 2021,
        "part_proprio": 63.6
    },
    {
        "codgeo": 56244,
        "libgeo": "Sérent",
        "an": 2021,
        "part_proprio": 77.2
    },
    {
        "codgeo": 56245,
        "libgeo": "Silfiac",
        "an": 2021,
        "part_proprio": 75.7
    },
    {
        "codgeo": 56246,
        "libgeo": "Le Sourn",
        "an": 2021,
        "part_proprio": 80.4
    },
    {
        "codgeo": 56247,
        "libgeo": "Sulniac",
        "an": 2021,
        "part_proprio": 76.3
    },
    {
        "codgeo": 56248,
        "libgeo": "Surzur",
        "an": 2021,
        "part_proprio": 77.8
    },
    {
        "codgeo": 56249,
        "libgeo": "Taupont",
        "an": 2021,
        "part_proprio": 80.7
    },
    {
        "codgeo": 56250,
        "libgeo": "Théhillac",
        "an": 2021,
        "part_proprio": 84.4
    },
    {
        "codgeo": 56251,
        "libgeo": "Theix-Noyalo",
        "an": 2021,
        "part_proprio": 70.3
    },
    {
        "codgeo": 56252,
        "libgeo": "Le Tour-du-Parc",
        "an": 2021,
        "part_proprio": 87.0
    },
    {
        "codgeo": 56253,
        "libgeo": "Tréal",
        "an": 2021,
        "part_proprio": 80.9
    },
    {
        "codgeo": 56254,
        "libgeo": "Trédion",
        "an": 2021,
        "part_proprio": 78.6
    },
    {
        "codgeo": 56255,
        "libgeo": "Treffléan",
        "an": 2021,
        "part_proprio": 80.8
    },
    {
        "codgeo": 56256,
        "libgeo": "Tréhorenteuc",
        "an": 2021,
        "part_proprio": 90.6
    },
    {
        "codgeo": 56257,
        "libgeo": "La Trinité-Porhoët",
        "an": 2021,
        "part_proprio": 81.2
    },
    {
        "codgeo": 56258,
        "libgeo": "La Trinité-sur-Mer",
        "an": 2021,
        "part_proprio": 72.5
    },
    {
        "codgeo": 56259,
        "libgeo": "La Trinité-Surzur",
        "an": 2021,
        "part_proprio": 72.0
    },
    {
        "codgeo": 56260,
        "libgeo": "Vannes",
        "an": 2021,
        "part_proprio": 45.2
    },
    {
        "codgeo": 56261,
        "libgeo": "La Vraie-Croix",
        "an": 2021,
        "part_proprio": 75.5
    },
    {
        "codgeo": 56262,
        "libgeo": "Le Bono",
        "an": 2021,
        "part_proprio": 76.8
    },
    {
        "codgeo": 56263,
        "libgeo": "Sainte-Anne-d'Auray",
        "an": 2021,
        "part_proprio": 69.4
    },
    {
        "codgeo": 56264,
        "libgeo": "Kernascléden",
        "an": 2021,
        "part_proprio": 72.3
    }
]