[
    {
        "Ville": "Avranches",
        "Code Postal": 50300,
        "Février 2025": 1180,
        "Janvier 2025": 1210,
        "Décembre 2024": 930,
        "Novembre 2024": 950,
        "Octobre 2024": 950,
        "Septembre 2024": 950,
        "Août 2024": 910,
        "Juillet 2024": 890,
        "Juin 2024": 910,
        "Mai 2024": 930,
        "Avril 2024": 910,
        "Mars 2024": 930,
        "Février 2024": 930,
        "Janvier 2024": 940,
        "Décembre 2023": 930,
        "Novembre 2023": 920,
        "Octobre 2023": 910,
        "Septembre 2023": 890,
        "Août 2023": 910,
        "Juillet 2023": 900,
        "Juin 2023": 890,
        "Mai 2023": 900,
        "Avril 2023": 900,
        "Mars 2023": 880,
        "Février 2023": 900,
        "Janvier 2023": 890,
        "Décembre 2022": 880,
        "Novembre 2022": 910,
        "Octobre 2022": 880,
        "Septembre 2022": 900,
        "Août 2022": 890,
        "Juillet 2022": 880,
        "Juin 2022": 870,
        "Mai 2022": 880,
        "Avril 2022": 890,
        "Mars 2022": 900,
        "Février 2022": 910,
        "Janvier 2022": 940,
        "Décembre 2021": 940,
        "Novembre 2021": 970,
        "Octobre 2021": 950,
        "Septembre 2021": 960,
        "Août 2021": 960,
        "Juillet 2021": 950,
        "Juin 2021": 980,
        "Mai 2021": 1000,
        "Avril 2021": 1030,
        "Mars 2021": 1030,
        "Février 2021": 1030,
        "Janvier 2021": 1040,
        "Décembre 2020": 1050,
        "Novembre 2020": 1040,
        "Octobre 2020": 1060,
        "Septembre 2020": 1050,
        "Août 2020": 1040,
        "Juillet 2020": 1030,
        "Juin 2020": 1060,
        "Mai 2020": 1090,
        "Avril 2020": 1080,
        "Mars 2020": 1050,
        "Février 2020": 1030,
        "Janvier 2020": 1020,
        "Décembre 2019": 1030,
        "Novembre 2019": 1010,
        "Octobre 2019": 920,
        "Septembre 2019": 880,
        "Août 2019": 880,
        "Juillet 2019": 870,
        "Juin 2019": 870,
        "Mai 2019": 850,
        "Avril 2019": 890,
        "Mars 2019": 870,
        "Février 2019": 880,
        "Janvier 2019": 880,
        "Décembre 2018": 880,
        "Novembre 2018": 870,
        "Octobre 2018": 870,
        "Septembre 2018": 870,
        "Août 2018": 850,
        "Juillet 2018": 840,
        "Juin 2018": 840,
        "Mai 2018": 860,
        "Avril 2018": 880,
        "Mars 2018": 880,
        "Février 2018": 880,
        "Janvier 2018": 860,
        "Décembre 2017": 820,
        "Novembre 2017": 840,
        "Octobre 2017": 830,
        "Septembre 2017": 810,
        "Août 2017": 810,
        "Juillet 2017": 810,
        "Juin 2017": 820,
        "Mai 2017": 830,
        "Avril 2017": 840,
        "Mars 2017": 850,
        "Février 2017": 860,
        "Janvier 2017": 860,
        "Décembre 2016": 860,
        "Novembre 2016": 870,
        "Octobre 2016": 840,
        "Septembre 2016": 850,
        "Août 2016": 820,
        "Juillet 2016": 800
    },
    {
        "Ville": "Bricquebec en Cotentin",
        "Code Postal": 50260,
        "Février 2025": 430,
        "Janvier 2025": 410,
        "Décembre 2024": 370,
        "Novembre 2024": 360,
        "Octobre 2024": 360,
        "Septembre 2024": 370,
        "Août 2024": 370,
        "Juillet 2024": 350,
        "Juin 2024": 350,
        "Mai 2024": 360,
        "Avril 2024": 360,
        "Mars 2024": 360,
        "Février 2024": 360,
        "Janvier 2024": 370,
        "Décembre 2023": 370,
        "Novembre 2023": 360,
        "Octobre 2023": 370,
        "Septembre 2023": 380,
        "Août 2023": 360,
        "Juillet 2023": 360,
        "Juin 2023": 360,
        "Mai 2023": 360,
        "Avril 2023": 370,
        "Mars 2023": 380,
        "Février 2023": 390,
        "Janvier 2023": 390,
        "Décembre 2022": 380,
        "Novembre 2022": 380,
        "Octobre 2022": 390,
        "Septembre 2022": 390,
        "Août 2022": 380,
        "Juillet 2022": 370,
        "Juin 2022": 380,
        "Mai 2022": 380,
        "Avril 2022": 380,
        "Mars 2022": 390,
        "Février 2022": 400,
        "Janvier 2022": 400,
        "Décembre 2021": 390,
        "Novembre 2021": 370,
        "Octobre 2021": 370,
        "Septembre 2021": 390,
        "Août 2021": 380,
        "Juillet 2021": 380,
        "Juin 2021": 390,
        "Mai 2021": 390,
        "Avril 2021": 400,
        "Mars 2021": 400,
        "Février 2021": 410,
        "Janvier 2021": 420,
        "Décembre 2020": 420,
        "Novembre 2020": 420,
        "Octobre 2020": 430,
        "Septembre 2020": 430,
        "Août 2020": 420,
        "Juillet 2020": 410,
        "Juin 2020": 420,
        "Mai 2020": 420,
        "Avril 2020": 440,
        "Mars 2020": 420,
        "Février 2020": 400,
        "Janvier 2020": 400,
        "Décembre 2019": 400,
        "Novembre 2019": 400,
        "Octobre 2019": 420,
        "Septembre 2019": 420,
        "Août 2019": 410,
        "Juillet 2019": 410,
        "Juin 2019": 400,
        "Mai 2019": 390,
        "Avril 2019": 400,
        "Mars 2019": 400,
        "Février 2019": 410,
        "Janvier 2019": 420,
        "Décembre 2018": 410,
        "Novembre 2018": 410,
        "Octobre 2018": 400,
        "Septembre 2018": 410,
        "Août 2018": 400,
        "Juillet 2018": 400,
        "Juin 2018": 390,
        "Mai 2018": 410,
        "Avril 2018": 420,
        "Mars 2018": 430,
        "Février 2018": 420,
        "Janvier 2018": 430,
        "Décembre 2017": 440,
        "Novembre 2017": 450,
        "Octobre 2017": 460,
        "Septembre 2017": 460,
        "Août 2017": 460,
        "Juillet 2017": 440,
        "Juin 2017": 450,
        "Mai 2017": 460,
        "Avril 2017": 460,
        "Mars 2017": 460,
        "Février 2017": 400,
        "Janvier 2017": 410,
        "Décembre 2016": 400,
        "Novembre 2016": 390,
        "Octobre 2016": 390,
        "Septembre 2016": 400,
        "Août 2016": 390,
        "Juillet 2016": 370
    },
    {
        "Ville": "Carentan",
        "Code Postal": 50500,
        "Février 2025": 830,
        "Janvier 2025": 830,
        "Décembre 2024": 640,
        "Novembre 2024": 630,
        "Octobre 2024": 650,
        "Septembre 2024": 640,
        "Août 2024": 610,
        "Juillet 2024": 600,
        "Juin 2024": 630,
        "Mai 2024": 650,
        "Avril 2024": 650,
        "Mars 2024": 680,
        "Février 2024": 690,
        "Janvier 2024": 690,
        "Décembre 2023": 680,
        "Novembre 2023": 690,
        "Octobre 2023": 680,
        "Septembre 2023": 670,
        "Août 2023": 660,
        "Juillet 2023": 650,
        "Juin 2023": 660,
        "Mai 2023": 670,
        "Avril 2023": 700,
        "Mars 2023": 710,
        "Février 2023": 700,
        "Janvier 2023": 710,
        "Décembre 2022": 700,
        "Novembre 2022": 700,
        "Octobre 2022": 710,
        "Septembre 2022": 710,
        "Août 2022": 700,
        "Juillet 2022": 700,
        "Juin 2022": 700,
        "Mai 2022": 710,
        "Avril 2022": 720,
        "Mars 2022": 740,
        "Février 2022": 740,
        "Janvier 2022": 740,
        "Décembre 2021": 750,
        "Novembre 2021": 760,
        "Octobre 2021": 760,
        "Septembre 2021": 770,
        "Août 2021": 780,
        "Juillet 2021": 780,
        "Juin 2021": 810,
        "Mai 2021": 820,
        "Avril 2021": 840,
        "Mars 2021": 830,
        "Février 2021": 850,
        "Janvier 2021": 870,
        "Décembre 2020": 870,
        "Novembre 2020": 880,
        "Octobre 2020": 880,
        "Septembre 2020": 860,
        "Août 2020": 850,
        "Juillet 2020": 810,
        "Juin 2020": 810,
        "Mai 2020": 840,
        "Avril 2020": 870,
        "Mars 2020": 840,
        "Février 2020": 840,
        "Janvier 2020": 840,
        "Décembre 2019": 860,
        "Novembre 2019": 870,
        "Octobre 2019": 760,
        "Septembre 2019": 750,
        "Août 2019": 740,
        "Juillet 2019": 730,
        "Juin 2019": 720,
        "Mai 2019": 730,
        "Avril 2019": 740,
        "Mars 2019": 740,
        "Février 2019": 750,
        "Janvier 2019": 740,
        "Décembre 2018": 750,
        "Novembre 2018": 760,
        "Octobre 2018": 760,
        "Septembre 2018": 750,
        "Août 2018": 730,
        "Juillet 2018": 700,
        "Juin 2018": 700,
        "Mai 2018": 710,
        "Avril 2018": 740,
        "Mars 2018": 750,
        "Février 2018": 760,
        "Janvier 2018": 760,
        "Décembre 2017": 760,
        "Novembre 2017": 780,
        "Octobre 2017": 750,
        "Septembre 2017": 740,
        "Août 2017": 710,
        "Juillet 2017": 690,
        "Juin 2017": 700,
        "Mai 2017": 700,
        "Avril 2017": 710,
        "Mars 2017": 720,
        "Février 2017": 690,
        "Janvier 2017": 680,
        "Décembre 2016": 660,
        "Novembre 2016": 660,
        "Octobre 2016": 670,
        "Septembre 2016": 670,
        "Août 2016": 670,
        "Juillet 2016": 650
    },
    {
        "Ville": "Cherbourg Octeville",
        "Code Postal": 50100,
        "Février 2025": 7670,
        "Janvier 2025": 7470,
        "Décembre 2024": 6390,
        "Novembre 2024": 6360,
        "Octobre 2024": 6460,
        "Septembre 2024": 6390,
        "Août 2024": 6120,
        "Juillet 2024": 6050,
        "Juin 2024": 6000,
        "Mai 2024": 6060,
        "Avril 2024": 6130,
        "Mars 2024": 6260,
        "Février 2024": 6380,
        "Janvier 2024": 6360,
        "Décembre 2023": 6230,
        "Novembre 2023": 6270,
        "Octobre 2023": 6240,
        "Septembre 2023": 6170,
        "Août 2023": 5990,
        "Juillet 2023": 5890,
        "Juin 2023": 5930,
        "Mai 2023": 6070,
        "Avril 2023": 6100,
        "Mars 2023": 6170,
        "Février 2023": 6190,
        "Janvier 2023": 6220,
        "Décembre 2022": 6160,
        "Novembre 2022": 6220,
        "Octobre 2022": 6230,
        "Septembre 2022": 6270,
        "Août 2022": 6150,
        "Juillet 2022": 5950,
        "Juin 2022": 6010,
        "Mai 2022": 6150,
        "Avril 2022": 6220,
        "Mars 2022": 6410,
        "Février 2022": 6480,
        "Janvier 2022": 6490,
        "Décembre 2021": 6450,
        "Novembre 2021": 6610,
        "Octobre 2021": 6620,
        "Septembre 2021": 6710,
        "Août 2021": 6530,
        "Juillet 2021": 6470,
        "Juin 2021": 6610,
        "Mai 2021": 6760,
        "Avril 2021": 6840,
        "Mars 2021": 7000,
        "Février 2021": 7040,
        "Janvier 2021": 7100,
        "Décembre 2020": 7110,
        "Novembre 2020": 7180,
        "Octobre 2020": 7240,
        "Septembre 2020": 7290,
        "Août 2020": 7200,
        "Juillet 2020": 7110,
        "Juin 2020": 7210,
        "Mai 2020": 7340,
        "Avril 2020": 7300,
        "Mars 2020": 7080,
        "Février 2020": 6890,
        "Janvier 2020": 6970,
        "Décembre 2019": 6850,
        "Novembre 2019": 6890,
        "Octobre 2019": 6980,
        "Septembre 2019": 5670,
        "Août 2019": 5500,
        "Juillet 2019": 5370,
        "Juin 2019": 5210,
        "Mai 2019": 5220,
        "Avril 2019": 5220,
        "Mars 2019": 5120,
        "Février 2019": 5150,
        "Janvier 2019": 5110,
        "Décembre 2018": 4840,
        "Novembre 2018": 4770,
        "Octobre 2018": 4690,
        "Septembre 2018": 4450,
        "Août 2018": 4090,
        "Juillet 2018": 3920,
        "Juin 2018": 3920,
        "Mai 2018": 4000,
        "Avril 2018": 4050,
        "Mars 2018": 4130,
        "Février 2018": 4200,
        "Janvier 2018": 4230,
        "Décembre 2017": 4200,
        "Novembre 2017": 4240,
        "Octobre 2017": 4240,
        "Septembre 2017": 4240,
        "Août 2017": 4190,
        "Juillet 2017": 4110,
        "Juin 2017": 4130,
        "Mai 2017": 4220,
        "Avril 2017": 4280,
        "Mars 2017": 4370,
        "Février 2017": 4370,
        "Janvier 2017": 4370,
        "Décembre 2016": 4280,
        "Novembre 2016": 4340,
        "Octobre 2016": 4260,
        "Septembre 2016": 4250,
        "Août 2016": 4120,
        "Juillet 2016": 4040
    },
    {
        "Ville": "Coutances",
        "Code Postal": 50200,
        "Février 2025": 1050,
        "Janvier 2025": 1030,
        "Décembre 2024": 840,
        "Novembre 2024": 840,
        "Octobre 2024": 850,
        "Septembre 2024": 850,
        "Août 2024": 820,
        "Juillet 2024": 800,
        "Juin 2024": 790,
        "Mai 2024": 800,
        "Avril 2024": 790,
        "Mars 2024": 790,
        "Février 2024": 790,
        "Janvier 2024": 810,
        "Décembre 2023": 780,
        "Novembre 2023": 810,
        "Octobre 2023": 810,
        "Septembre 2023": 820,
        "Août 2023": 790,
        "Juillet 2023": 770,
        "Juin 2023": 770,
        "Mai 2023": 770,
        "Avril 2023": 780,
        "Mars 2023": 820,
        "Février 2023": 820,
        "Janvier 2023": 820,
        "Décembre 2022": 790,
        "Novembre 2022": 790,
        "Octobre 2022": 790,
        "Septembre 2022": 800,
        "Août 2022": 770,
        "Juillet 2022": 760,
        "Juin 2022": 780,
        "Mai 2022": 780,
        "Avril 2022": 760,
        "Mars 2022": 780,
        "Février 2022": 780,
        "Janvier 2022": 790,
        "Décembre 2021": 810,
        "Novembre 2021": 830,
        "Octobre 2021": 840,
        "Septembre 2021": 840,
        "Août 2021": 840,
        "Juillet 2021": 840,
        "Juin 2021": 860,
        "Mai 2021": 860,
        "Avril 2021": 870,
        "Mars 2021": 880,
        "Février 2021": 890,
        "Janvier 2021": 900,
        "Décembre 2020": 890,
        "Novembre 2020": 900,
        "Octobre 2020": 890,
        "Septembre 2020": 910,
        "Août 2020": 880,
        "Juillet 2020": 900,
        "Juin 2020": 900,
        "Mai 2020": 920,
        "Avril 2020": 920,
        "Mars 2020": 900,
        "Février 2020": 900,
        "Janvier 2020": 900,
        "Décembre 2019": 890,
        "Novembre 2019": 890,
        "Octobre 2019": 880,
        "Septembre 2019": 870,
        "Août 2019": 880,
        "Juillet 2019": 880,
        "Juin 2019": 890,
        "Mai 2019": 900,
        "Avril 2019": 930,
        "Mars 2019": 930,
        "Février 2019": 920,
        "Janvier 2019": 940,
        "Décembre 2018": 910,
        "Novembre 2018": 930,
        "Octobre 2018": 940,
        "Septembre 2018": 920,
        "Août 2018": 910,
        "Juillet 2018": 900,
        "Juin 2018": 880,
        "Mai 2018": 890,
        "Avril 2018": 890,
        "Mars 2018": 910,
        "Février 2018": 950,
        "Janvier 2018": 950,
        "Décembre 2017": 930,
        "Novembre 2017": 950,
        "Octobre 2017": 950,
        "Septembre 2017": 930,
        "Août 2017": 920,
        "Juillet 2017": 900,
        "Juin 2017": 910,
        "Mai 2017": 940,
        "Avril 2017": 940,
        "Mars 2017": 950,
        "Février 2017": 950,
        "Janvier 2017": 950,
        "Décembre 2016": 940,
        "Novembre 2016": 970,
        "Octobre 2016": 990,
        "Septembre 2016": 980,
        "Août 2016": 960,
        "Juillet 2016": 930
    },
    {
        "Ville": "Equeurdreville Hainneville",
        "Code Postal": 50120,
        "Février 2025": 0,
        "Janvier 2025": 0,
        "Décembre 2024": 0,
        "Novembre 2024": 0,
        "Octobre 2024": 0,
        "Septembre 2024": 0,
        "Août 2024": 0,
        "Juillet 2024": 0,
        "Juin 2024": 0,
        "Mai 2024": 0,
        "Avril 2024": 0,
        "Mars 2024": 0,
        "Février 2024": 0,
        "Janvier 2024": 0,
        "Décembre 2023": 0,
        "Novembre 2023": 0,
        "Octobre 2023": 0,
        "Septembre 2023": 0,
        "Août 2023": 0,
        "Juillet 2023": 0,
        "Juin 2023": 0,
        "Mai 2023": 0,
        "Avril 2023": 0,
        "Mars 2023": 0,
        "Février 2023": 0,
        "Janvier 2023": 0,
        "Décembre 2022": 0,
        "Novembre 2022": 0,
        "Octobre 2022": 0,
        "Septembre 2022": 0,
        "Août 2022": 0,
        "Juillet 2022": 0,
        "Juin 2022": 0,
        "Mai 2022": 0,
        "Avril 2022": 0,
        "Mars 2022": 0,
        "Février 2022": 0,
        "Janvier 2022": 0,
        "Décembre 2021": 0,
        "Novembre 2021": 0,
        "Octobre 2021": 0,
        "Septembre 2021": 0,
        "Août 2021": 0,
        "Juillet 2021": 0,
        "Juin 2021": 0,
        "Mai 2021": 0,
        "Avril 2021": 0,
        "Mars 2021": 0,
        "Février 2021": 0,
        "Janvier 2021": 0,
        "Décembre 2020": 0,
        "Novembre 2020": 0,
        "Octobre 2020": 0,
        "Septembre 2020": 0,
        "Août 2020": 0,
        "Juillet 2020": 0,
        "Juin 2020": 0,
        "Mai 2020": 0,
        "Avril 2020": 0,
        "Mars 2020": 0,
        "Février 2020": 0,
        "Janvier 2020": 0,
        "Décembre 2019": 0,
        "Novembre 2019": 0,
        "Octobre 2019": 0,
        "Septembre 2019": 570,
        "Août 2019": 610,
        "Juillet 2019": 640,
        "Juin 2019": 690,
        "Mai 2019": 730,
        "Avril 2019": 760,
        "Mars 2019": 800,
        "Février 2019": 860,
        "Janvier 2019": 900,
        "Décembre 2018": 950,
        "Novembre 2018": 1030,
        "Octobre 2018": 1110,
        "Septembre 2018": 1170,
        "Août 2018": 1270,
        "Juillet 2018": 1290,
        "Juin 2018": 1260,
        "Mai 2018": 1290,
        "Avril 2018": 1330,
        "Mars 2018": 1350,
        "Février 2018": 1340,
        "Janvier 2018": 1370,
        "Décembre 2017": 1350,
        "Novembre 2017": 1380,
        "Octobre 2017": 1370,
        "Septembre 2017": 1360,
        "Août 2017": 1350,
        "Juillet 2017": 1330,
        "Juin 2017": 1330,
        "Mai 2017": 1360,
        "Avril 2017": 1380,
        "Mars 2017": 1420,
        "Février 2017": 1430,
        "Janvier 2017": 1460,
        "Décembre 2016": 1470,
        "Novembre 2016": 1500,
        "Octobre 2016": 1500,
        "Septembre 2016": 1490,
        "Août 2016": 1440,
        "Juillet 2016": 1370
    },
    {
        "Ville": "Granville",
        "Code Postal": 50400,
        "Février 2025": 1430,
        "Janvier 2025": 1450,
        "Décembre 2024": 1200,
        "Novembre 2024": 1190,
        "Octobre 2024": 1180,
        "Septembre 2024": 1160,
        "Août 2024": 1120,
        "Juillet 2024": 1090,
        "Juin 2024": 1110,
        "Mai 2024": 1120,
        "Avril 2024": 1130,
        "Mars 2024": 1150,
        "Février 2024": 1140,
        "Janvier 2024": 1150,
        "Décembre 2023": 1140,
        "Novembre 2023": 1130,
        "Octobre 2023": 1120,
        "Septembre 2023": 1100,
        "Août 2023": 1090,
        "Juillet 2023": 1070,
        "Juin 2023": 1050,
        "Mai 2023": 1050,
        "Avril 2023": 1080,
        "Mars 2023": 1110,
        "Février 2023": 1100,
        "Janvier 2023": 1100,
        "Décembre 2022": 1110,
        "Novembre 2022": 1100,
        "Octobre 2022": 1100,
        "Septembre 2022": 1090,
        "Août 2022": 1060,
        "Juillet 2022": 1040,
        "Juin 2022": 1050,
        "Mai 2022": 1080,
        "Avril 2022": 1100,
        "Mars 2022": 1130,
        "Février 2022": 1140,
        "Janvier 2022": 1140,
        "Décembre 2021": 1160,
        "Novembre 2021": 1190,
        "Octobre 2021": 1180,
        "Septembre 2021": 1210,
        "Août 2021": 1220,
        "Juillet 2021": 1220,
        "Juin 2021": 1250,
        "Mai 2021": 1270,
        "Avril 2021": 1300,
        "Mars 2021": 1310,
        "Février 2021": 1310,
        "Janvier 2021": 1320,
        "Décembre 2020": 1310,
        "Novembre 2020": 1310,
        "Octobre 2020": 1290,
        "Septembre 2020": 1300,
        "Août 2020": 1280,
        "Juillet 2020": 1270,
        "Juin 2020": 1250,
        "Mai 2020": 1250,
        "Avril 2020": 1280,
        "Mars 2020": 1260,
        "Février 2020": 1230,
        "Janvier 2020": 1240,
        "Décembre 2019": 1260,
        "Novembre 2019": 1280,
        "Octobre 2019": 1270,
        "Septembre 2019": 1240,
        "Août 2019": 1220,
        "Juillet 2019": 1190,
        "Juin 2019": 1200,
        "Mai 2019": 1210,
        "Avril 2019": 1250,
        "Mars 2019": 1280,
        "Février 2019": 1290,
        "Janvier 2019": 1310,
        "Décembre 2018": 1300,
        "Novembre 2018": 1300,
        "Octobre 2018": 1300,
        "Septembre 2018": 1260,
        "Août 2018": 1210,
        "Juillet 2018": 1200,
        "Juin 2018": 1200,
        "Mai 2018": 1260,
        "Avril 2018": 1260,
        "Mars 2018": 1290,
        "Février 2018": 1290,
        "Janvier 2018": 1270,
        "Décembre 2017": 1290,
        "Novembre 2017": 1310,
        "Octobre 2017": 1300,
        "Septembre 2017": 1250,
        "Août 2017": 1210,
        "Juillet 2017": 1180,
        "Juin 2017": 1200,
        "Mai 2017": 1220,
        "Avril 2017": 1220,
        "Mars 2017": 1250,
        "Février 2017": 1270,
        "Janvier 2017": 1290,
        "Décembre 2016": 1270,
        "Novembre 2016": 1280,
        "Octobre 2016": 1250,
        "Septembre 2016": 1260,
        "Août 2016": 1210,
        "Juillet 2016": 1160
    },
    {
        "Ville": "LaGlacerie",
        "Code Postal": 50470,
        "Février 2025": 0,
        "Janvier 2025": 0,
        "Décembre 2024": 0,
        "Novembre 2024": 0,
        "Octobre 2024": 0,
        "Septembre 2024": 0,
        "Août 2024": 0,
        "Juillet 2024": 0,
        "Juin 2024": 0,
        "Mai 2024": 0,
        "Avril 2024": 0,
        "Mars 2024": 0,
        "Février 2024": 0,
        "Janvier 2024": 0,
        "Décembre 2023": 0,
        "Novembre 2023": 0,
        "Octobre 2023": 0,
        "Septembre 2023": 0,
        "Août 2023": 0,
        "Juillet 2023": 0,
        "Juin 2023": 0,
        "Mai 2023": 0,
        "Avril 2023": 0,
        "Mars 2023": 0,
        "Février 2023": 0,
        "Janvier 2023": 0,
        "Décembre 2022": 0,
        "Novembre 2022": 0,
        "Octobre 2022": 0,
        "Septembre 2022": 0,
        "Août 2022": 0,
        "Juillet 2022": 0,
        "Juin 2022": 0,
        "Mai 2022": 0,
        "Avril 2022": 0,
        "Mars 2022": 0,
        "Février 2022": 0,
        "Janvier 2022": 0,
        "Décembre 2021": 0,
        "Novembre 2021": 0,
        "Octobre 2021": 0,
        "Septembre 2021": 0,
        "Août 2021": 0,
        "Juillet 2021": 0,
        "Juin 2021": 0,
        "Mai 2021": 0,
        "Avril 2021": 0,
        "Mars 2021": 0,
        "Février 2021": 0,
        "Janvier 2021": 0,
        "Décembre 2020": 0,
        "Novembre 2020": 0,
        "Octobre 2020": 0,
        "Septembre 2020": 0,
        "Août 2020": 0,
        "Juillet 2020": 0,
        "Juin 2020": 0,
        "Mai 2020": 0,
        "Avril 2020": 0,
        "Mars 2020": 0,
        "Février 2020": 0,
        "Janvier 2020": 0,
        "Décembre 2019": 0,
        "Novembre 2019": 0,
        "Octobre 2019": 0,
        "Septembre 2019": 180,
        "Août 2019": 190,
        "Juillet 2019": 200,
        "Juin 2019": 220,
        "Mai 2019": 240,
        "Avril 2019": 260,
        "Mars 2019": 270,
        "Février 2019": 290,
        "Janvier 2019": 320,
        "Décembre 2018": 340,
        "Novembre 2018": 370,
        "Octobre 2018": 400,
        "Septembre 2018": 410,
        "Août 2018": 400,
        "Juillet 2018": 390,
        "Juin 2018": 400,
        "Mai 2018": 420,
        "Avril 2018": 440,
        "Mars 2018": 440,
        "Février 2018": 460,
        "Janvier 2018": 450,
        "Décembre 2017": 440,
        "Novembre 2017": 460,
        "Octobre 2017": 480,
        "Septembre 2017": 480,
        "Août 2017": 490,
        "Juillet 2017": 470,
        "Juin 2017": 490,
        "Mai 2017": 490,
        "Avril 2017": 490,
        "Mars 2017": 500,
        "Février 2017": 520,
        "Janvier 2017": 510,
        "Décembre 2016": 510,
        "Novembre 2016": 510,
        "Octobre 2016": 500,
        "Septembre 2016": 510,
        "Août 2016": 500,
        "Juillet 2016": 490
    },
    {
        "Ville": "LaHague",
        "Code Postal": 50440,
        "Février 2025": 690,
        "Janvier 2025": 680,
        "Décembre 2024": 650,
        "Novembre 2024": 650,
        "Octobre 2024": 650,
        "Septembre 2024": 650,
        "Août 2024": 630,
        "Juillet 2024": 630,
        "Juin 2024": 610,
        "Mai 2024": 630,
        "Avril 2024": 640,
        "Mars 2024": 670,
        "Février 2024": 680,
        "Janvier 2024": 690,
        "Décembre 2023": 690,
        "Novembre 2023": 690,
        "Octobre 2023": 680,
        "Septembre 2023": 690,
        "Août 2023": 670,
        "Juillet 2023": 640,
        "Juin 2023": 630,
        "Mai 2023": 630,
        "Avril 2023": 630,
        "Mars 2023": 650,
        "Février 2023": 670,
        "Janvier 2023": 660,
        "Décembre 2022": 660,
        "Novembre 2022": 670,
        "Octobre 2022": 680,
        "Septembre 2022": 670,
        "Août 2022": 670,
        "Juillet 2022": 670,
        "Juin 2022": 680,
        "Mai 2022": 680,
        "Avril 2022": 710,
        "Mars 2022": 730,
        "Février 2022": 750,
        "Janvier 2022": 760,
        "Décembre 2021": 740,
        "Novembre 2021": 750,
        "Octobre 2021": 750,
        "Septembre 2021": 750,
        "Août 2021": 730,
        "Juillet 2021": 710,
        "Juin 2021": 710,
        "Mai 2021": 700,
        "Avril 2021": 720,
        "Mars 2021": 730,
        "Février 2021": 750,
        "Janvier 2021": 750,
        "Décembre 2020": 770,
        "Novembre 2020": 760,
        "Octobre 2020": 760,
        "Septembre 2020": 760,
        "Août 2020": 760,
        "Juillet 2020": 750,
        "Juin 2020": 750,
        "Mai 2020": 780,
        "Avril 2020": 790,
        "Mars 2020": 760,
        "Février 2020": 730,
        "Janvier 2020": 740,
        "Décembre 2019": 740,
        "Novembre 2019": 720,
        "Octobre 2019": 740,
        "Septembre 2019": 640,
        "Août 2019": 610,
        "Juillet 2019": 610,
        "Juin 2019": 600,
        "Mai 2019": 620,
        "Avril 2019": 610,
        "Mars 2019": 620,
        "Février 2019": 640,
        "Janvier 2019": 650,
        "Décembre 2018": 640,
        "Novembre 2018": 630,
        "Octobre 2018": 610,
        "Septembre 2018": 610,
        "Août 2018": 570,
        "Juillet 2018": 550,
        "Juin 2018": 520,
        "Mai 2018": 530,
        "Avril 2018": 530,
        "Mars 2018": 510,
        "Février 2018": 520,
        "Janvier 2018": 500,
        "Décembre 2017": 470,
        "Novembre 2017": 440,
        "Octobre 2017": 410,
        "Septembre 2017": 400,
        "Août 2017": 360,
        "Juillet 2017": 330,
        "Juin 2017": 290,
        "Mai 2017": 260,
        "Avril 2017": 240,
        "Mars 2017": 210,
        "Février 2017": 190,
        "Janvier 2017": 150,
        "Décembre 2016": 140,
        "Novembre 2016": 140,
        "Octobre 2016": 140,
        "Septembre 2016": 140,
        "Août 2016": 130,
        "Juillet 2016": 130
    },
    {
        "Ville": "Querqueville",
        "Code Postal": 50460,
        "Février 2025": 0,
        "Janvier 2025": 0,
        "Décembre 2024": 0,
        "Novembre 2024": 0,
        "Octobre 2024": 0,
        "Septembre 2024": 0,
        "Août 2024": 0,
        "Juillet 2024": 0,
        "Juin 2024": 0,
        "Mai 2024": 0,
        "Avril 2024": 0,
        "Mars 2024": 0,
        "Février 2024": 0,
        "Janvier 2024": 0,
        "Décembre 2023": 0,
        "Novembre 2023": 0,
        "Octobre 2023": 0,
        "Septembre 2023": 0,
        "Août 2023": 0,
        "Juillet 2023": 0,
        "Juin 2023": 0,
        "Mai 2023": 0,
        "Avril 2023": 0,
        "Mars 2023": 0,
        "Février 2023": 0,
        "Janvier 2023": 0,
        "Décembre 2022": 0,
        "Novembre 2022": 0,
        "Octobre 2022": 0,
        "Septembre 2022": 0,
        "Août 2022": 0,
        "Juillet 2022": 0,
        "Juin 2022": 0,
        "Mai 2022": 0,
        "Avril 2022": 0,
        "Mars 2022": 0,
        "Février 2022": 0,
        "Janvier 2022": 0,
        "Décembre 2021": 0,
        "Novembre 2021": 0,
        "Octobre 2021": 0,
        "Septembre 2021": 0,
        "Août 2021": 0,
        "Juillet 2021": 0,
        "Juin 2021": 0,
        "Mai 2021": 0,
        "Avril 2021": 0,
        "Mars 2021": 0,
        "Février 2021": 0,
        "Janvier 2021": 0,
        "Décembre 2020": 0,
        "Novembre 2020": 0,
        "Octobre 2020": 0,
        "Septembre 2020": 0,
        "Août 2020": 0,
        "Juillet 2020": 0,
        "Juin 2020": 0,
        "Mai 2020": 0,
        "Avril 2020": 0,
        "Mars 2020": 0,
        "Février 2020": 0,
        "Janvier 2020": 0,
        "Décembre 2019": 0,
        "Novembre 2019": 0,
        "Octobre 2019": 0,
        "Septembre 2019": 140,
        "Août 2019": 150,
        "Juillet 2019": 170,
        "Juin 2019": 180,
        "Mai 2019": 190,
        "Avril 2019": 210,
        "Mars 2019": 220,
        "Février 2019": 230,
        "Janvier 2019": 250,
        "Décembre 2018": 270,
        "Novembre 2018": 280,
        "Octobre 2018": 310,
        "Septembre 2018": 330,
        "Août 2018": 350,
        "Juillet 2018": 350,
        "Juin 2018": 350,
        "Mai 2018": 370,
        "Avril 2018": 370,
        "Mars 2018": 380,
        "Février 2018": 370,
        "Janvier 2018": 380,
        "Décembre 2017": 380,
        "Novembre 2017": 390,
        "Octobre 2017": 390,
        "Septembre 2017": 380,
        "Août 2017": 380,
        "Juillet 2017": 360,
        "Juin 2017": 350,
        "Mai 2017": 360,
        "Avril 2017": 360,
        "Mars 2017": 380,
        "Février 2017": 390,
        "Janvier 2017": 390,
        "Décembre 2016": 400,
        "Novembre 2016": 390,
        "Octobre 2016": 410,
        "Septembre 2016": 410,
        "Août 2016": 400,
        "Juillet 2016": 390
    },
    {
        "Ville": "st Hilaire du Harcouet",
        "Code Postal": 50600,
        "Février 2025": 520,
        "Janvier 2025": 540,
        "Décembre 2024": 440,
        "Novembre 2024": 450,
        "Octobre 2024": 450,
        "Septembre 2024": 450,
        "Août 2024": 430,
        "Juillet 2024": 430,
        "Juin 2024": 440,
        "Mai 2024": 450,
        "Avril 2024": 460,
        "Mars 2024": 440,
        "Février 2024": 450,
        "Janvier 2024": 460,
        "Décembre 2023": 440,
        "Novembre 2023": 430,
        "Octobre 2023": 430,
        "Septembre 2023": 420,
        "Août 2023": 420,
        "Juillet 2023": 420,
        "Juin 2023": 410,
        "Mai 2023": 430,
        "Avril 2023": 420,
        "Mars 2023": 430,
        "Février 2023": 420,
        "Janvier 2023": 430,
        "Décembre 2022": 420,
        "Novembre 2022": 420,
        "Octobre 2022": 410,
        "Septembre 2022": 410,
        "Août 2022": 410,
        "Juillet 2022": 400,
        "Juin 2022": 410,
        "Mai 2022": 420,
        "Avril 2022": 420,
        "Mars 2022": 440,
        "Février 2022": 440,
        "Janvier 2022": 440,
        "Décembre 2021": 440,
        "Novembre 2021": 450,
        "Octobre 2021": 450,
        "Septembre 2021": 470,
        "Août 2021": 470,
        "Juillet 2021": 450,
        "Juin 2021": 460,
        "Mai 2021": 460,
        "Avril 2021": 470,
        "Mars 2021": 470,
        "Février 2021": 480,
        "Janvier 2021": 480,
        "Décembre 2020": 450,
        "Novembre 2020": 440,
        "Octobre 2020": 450,
        "Septembre 2020": 450,
        "Août 2020": 430,
        "Juillet 2020": 440,
        "Juin 2020": 440,
        "Mai 2020": 430,
        "Avril 2020": 430,
        "Mars 2020": 430,
        "Février 2020": 430,
        "Janvier 2020": 420,
        "Décembre 2019": 410,
        "Novembre 2019": 400,
        "Octobre 2019": 410,
        "Septembre 2019": 410,
        "Août 2019": 390,
        "Juillet 2019": 390,
        "Juin 2019": 390,
        "Mai 2019": 400,
        "Avril 2019": 400,
        "Mars 2019": 400,
        "Février 2019": 420,
        "Janvier 2019": 430,
        "Décembre 2018": 420,
        "Novembre 2018": 420,
        "Octobre 2018": 430,
        "Septembre 2018": 410,
        "Août 2018": 390,
        "Juillet 2018": 370,
        "Juin 2018": 370,
        "Mai 2018": 400,
        "Avril 2018": 390,
        "Mars 2018": 400,
        "Février 2018": 400,
        "Janvier 2018": 410,
        "Décembre 2017": 410,
        "Novembre 2017": 410,
        "Octobre 2017": 410,
        "Septembre 2017": 410,
        "Août 2017": 410,
        "Juillet 2017": 390,
        "Juin 2017": 380,
        "Mai 2017": 390,
        "Avril 2017": 390,
        "Mars 2017": 400,
        "Février 2017": 360,
        "Janvier 2017": 360,
        "Décembre 2016": 350,
        "Novembre 2016": 340,
        "Octobre 2016": 330,
        "Septembre 2016": 320,
        "Août 2016": 320,
        "Juillet 2016": 300
    },
    {
        "Ville": "st Lo",
        "Code Postal": 50000,
        "Février 2025": 2410,
        "Janvier 2025": 2340,
        "Décembre 2024": 1940,
        "Novembre 2024": 1920,
        "Octobre 2024": 1910,
        "Septembre 2024": 1900,
        "Août 2024": 1830,
        "Juillet 2024": 1850,
        "Juin 2024": 1820,
        "Mai 2024": 1840,
        "Avril 2024": 1860,
        "Mars 2024": 1860,
        "Février 2024": 1860,
        "Janvier 2024": 1890,
        "Décembre 2023": 1860,
        "Novembre 2023": 1860,
        "Octobre 2023": 1850,
        "Septembre 2023": 1820,
        "Août 2023": 1820,
        "Juillet 2023": 1780,
        "Juin 2023": 1780,
        "Mai 2023": 1790,
        "Avril 2023": 1790,
        "Mars 2023": 1830,
        "Février 2023": 1830,
        "Janvier 2023": 1830,
        "Décembre 2022": 1800,
        "Novembre 2022": 1820,
        "Octobre 2022": 1810,
        "Septembre 2022": 1810,
        "Août 2022": 1790,
        "Juillet 2022": 1770,
        "Juin 2022": 1770,
        "Mai 2022": 1790,
        "Avril 2022": 1810,
        "Mars 2022": 1850,
        "Février 2022": 1850,
        "Janvier 2022": 1860,
        "Décembre 2021": 1890,
        "Novembre 2021": 1910,
        "Octobre 2021": 1910,
        "Septembre 2021": 1930,
        "Août 2021": 1920,
        "Juillet 2021": 1870,
        "Juin 2021": 1910,
        "Mai 2021": 1930,
        "Avril 2021": 1960,
        "Mars 2021": 2000,
        "Février 2021": 2020,
        "Janvier 2021": 2060,
        "Décembre 2020": 2060,
        "Novembre 2020": 2050,
        "Octobre 2020": 2020,
        "Septembre 2020": 2030,
        "Août 2020": 1990,
        "Juillet 2020": 1970,
        "Juin 2020": 1990,
        "Mai 2020": 2010,
        "Avril 2020": 2010,
        "Mars 2020": 1990,
        "Février 2020": 1940,
        "Janvier 2020": 2000,
        "Décembre 2019": 1960,
        "Novembre 2019": 1990,
        "Octobre 2019": 2010,
        "Septembre 2019": 2020,
        "Août 2019": 1980,
        "Juillet 2019": 1990,
        "Juin 2019": 2010,
        "Mai 2019": 2010,
        "Avril 2019": 2020,
        "Mars 2019": 2030,
        "Février 2019": 2040,
        "Janvier 2019": 2110,
        "Décembre 2018": 2080,
        "Novembre 2018": 2090,
        "Octobre 2018": 2100,
        "Septembre 2018": 2090,
        "Août 2018": 2070,
        "Juillet 2018": 1990,
        "Juin 2018": 2030,
        "Mai 2018": 2060,
        "Avril 2018": 2090,
        "Mars 2018": 2100,
        "Février 2018": 2090,
        "Janvier 2018": 2080,
        "Décembre 2017": 2070,
        "Novembre 2017": 2120,
        "Octobre 2017": 2140,
        "Septembre 2017": 2100,
        "Août 2017": 2080,
        "Juillet 2017": 2020,
        "Juin 2017": 2050,
        "Mai 2017": 2070,
        "Avril 2017": 2050,
        "Mars 2017": 2050,
        "Février 2017": 2050,
        "Janvier 2017": 2080,
        "Décembre 2016": 2050,
        "Novembre 2016": 2040,
        "Octobre 2016": 2070,
        "Septembre 2016": 2070,
        "Août 2016": 2040,
        "Juillet 2016": 1990
    },
    {
        "Ville": "Tourlaville",
        "Code Postal": 50110,
        "Février 2025": 0,
        "Janvier 2025": 0,
        "Décembre 2024": 0,
        "Novembre 2024": 0,
        "Octobre 2024": 0,
        "Septembre 2024": 0,
        "Août 2024": 0,
        "Juillet 2024": 0,
        "Juin 2024": 0,
        "Mai 2024": 0,
        "Avril 2024": 0,
        "Mars 2024": 0,
        "Février 2024": 0,
        "Janvier 2024": 0,
        "Décembre 2023": 0,
        "Novembre 2023": 0,
        "Octobre 2023": 0,
        "Septembre 2023": 0,
        "Août 2023": 0,
        "Juillet 2023": 0,
        "Juin 2023": 0,
        "Mai 2023": 0,
        "Avril 2023": 0,
        "Mars 2023": 0,
        "Février 2023": 0,
        "Janvier 2023": 0,
        "Décembre 2022": 0,
        "Novembre 2022": 0,
        "Octobre 2022": 0,
        "Septembre 2022": 0,
        "Août 2022": 0,
        "Juillet 2022": 0,
        "Juin 2022": 0,
        "Mai 2022": 0,
        "Avril 2022": 0,
        "Mars 2022": 0,
        "Février 2022": 0,
        "Janvier 2022": 0,
        "Décembre 2021": 0,
        "Novembre 2021": 0,
        "Octobre 2021": 0,
        "Septembre 2021": 0,
        "Août 2021": 0,
        "Juillet 2021": 0,
        "Juin 2021": 0,
        "Mai 2021": 0,
        "Avril 2021": 0,
        "Mars 2021": 0,
        "Février 2021": 0,
        "Janvier 2021": 0,
        "Décembre 2020": 0,
        "Novembre 2020": 0,
        "Octobre 2020": 0,
        "Septembre 2020": 0,
        "Août 2020": 0,
        "Juillet 2020": 0,
        "Juin 2020": 0,
        "Mai 2020": 0,
        "Avril 2020": 0,
        "Mars 2020": 0,
        "Février 2020": 0,
        "Janvier 2020": 0,
        "Décembre 2019": 0,
        "Novembre 2019": 0,
        "Octobre 2019": 10,
        "Septembre 2019": 450,
        "Août 2019": 490,
        "Juillet 2019": 530,
        "Juin 2019": 580,
        "Mai 2019": 620,
        "Avril 2019": 660,
        "Mars 2019": 710,
        "Février 2019": 770,
        "Janvier 2019": 820,
        "Décembre 2018": 890,
        "Novembre 2018": 950,
        "Octobre 2018": 1020,
        "Septembre 2018": 1100,
        "Août 2018": 1190,
        "Juillet 2018": 1220,
        "Juin 2018": 1210,
        "Mai 2018": 1260,
        "Avril 2018": 1270,
        "Mars 2018": 1280,
        "Février 2018": 1320,
        "Janvier 2018": 1350,
        "Décembre 2017": 1340,
        "Novembre 2017": 1350,
        "Octobre 2017": 1360,
        "Septembre 2017": 1360,
        "Août 2017": 1320,
        "Juillet 2017": 1300,
        "Juin 2017": 1310,
        "Mai 2017": 1340,
        "Avril 2017": 1360,
        "Mars 2017": 1360,
        "Février 2017": 1360,
        "Janvier 2017": 1390,
        "Décembre 2016": 1390,
        "Novembre 2016": 1430,
        "Octobre 2016": 1430,
        "Septembre 2016": 1430,
        "Août 2016": 1370,
        "Juillet 2016": 1330
    },
    {
        "Ville": "Valognes",
        "Code Postal": 50700,
        "Février 2025": 500,
        "Janvier 2025": 510,
        "Décembre 2024": 440,
        "Novembre 2024": 440,
        "Octobre 2024": 430,
        "Septembre 2024": 400,
        "Août 2024": 390,
        "Juillet 2024": 400,
        "Juin 2024": 400,
        "Mai 2024": 390,
        "Avril 2024": 390,
        "Mars 2024": 390,
        "Février 2024": 400,
        "Janvier 2024": 400,
        "Décembre 2023": 410,
        "Novembre 2023": 410,
        "Octobre 2023": 410,
        "Septembre 2023": 410,
        "Août 2023": 400,
        "Juillet 2023": 390,
        "Juin 2023": 400,
        "Mai 2023": 430,
        "Avril 2023": 430,
        "Mars 2023": 440,
        "Février 2023": 440,
        "Janvier 2023": 440,
        "Décembre 2022": 440,
        "Novembre 2022": 450,
        "Octobre 2022": 440,
        "Septembre 2022": 420,
        "Août 2022": 420,
        "Juillet 2022": 410,
        "Juin 2022": 410,
        "Mai 2022": 410,
        "Avril 2022": 410,
        "Mars 2022": 420,
        "Février 2022": 430,
        "Janvier 2022": 440,
        "Décembre 2021": 450,
        "Novembre 2021": 470,
        "Octobre 2021": 460,
        "Septembre 2021": 470,
        "Août 2021": 470,
        "Juillet 2021": 450,
        "Juin 2021": 450,
        "Mai 2021": 470,
        "Avril 2021": 480,
        "Mars 2021": 500,
        "Février 2021": 480,
        "Janvier 2021": 480,
        "Décembre 2020": 490,
        "Novembre 2020": 500,
        "Octobre 2020": 490,
        "Septembre 2020": 490,
        "Août 2020": 490,
        "Juillet 2020": 480,
        "Juin 2020": 500,
        "Mai 2020": 500,
        "Avril 2020": 510,
        "Mars 2020": 490,
        "Février 2020": 480,
        "Janvier 2020": 490,
        "Décembre 2019": 490,
        "Novembre 2019": 500,
        "Octobre 2019": 500,
        "Septembre 2019": 510,
        "Août 2019": 480,
        "Juillet 2019": 480,
        "Juin 2019": 490,
        "Mai 2019": 500,
        "Avril 2019": 510,
        "Mars 2019": 510,
        "Février 2019": 510,
        "Janvier 2019": 520,
        "Décembre 2018": 540,
        "Novembre 2018": 530,
        "Octobre 2018": 540,
        "Septembre 2018": 550,
        "Août 2018": 550,
        "Juillet 2018": 550,
        "Juin 2018": 520,
        "Mai 2018": 540,
        "Avril 2018": 560,
        "Mars 2018": 580,
        "Février 2018": 590,
        "Janvier 2018": 590,
        "Décembre 2017": 600,
        "Novembre 2017": 600,
        "Octobre 2017": 590,
        "Septembre 2017": 590,
        "Août 2017": 570,
        "Juillet 2017": 570,
        "Juin 2017": 570,
        "Mai 2017": 560,
        "Avril 2017": 560,
        "Mars 2017": 570,
        "Février 2017": 590,
        "Janvier 2017": 590,
        "Décembre 2016": 580,
        "Novembre 2016": 580,
        "Octobre 2016": 570,
        "Septembre 2016": 570,
        "Août 2016": 550,
        "Juillet 2016": 550
    }
]